gee2gpd/__init__.py
gee2gpd/convert.py
gee2gpd/dfutils.py
gee2gpd/main.py
gee2gpd-0.2.0.dist-info/METADATA
gee2gpd-0.2.0.dist-info/WHEEL
gee2gpd-0.2.0.dist-info/entry_points.txt
gee2gpd-0.2.0.dist-info/top_level.txt
gee2gpd-0.2.0.dist-info/RECORD
